bluez_peripheral/__init__.py
bluez_peripheral/advert.py
bluez_peripheral/agent.py
bluez_peripheral/util.py
bluez_peripheral/uuid.py
bluez_peripheral/gatt/__init__.py
bluez_peripheral/gatt/characteristic.py
bluez_peripheral/gatt/descriptor.py
bluez_peripheral/gatt/service.py
tests/gatt/__init__.py
tests/gatt/test_characteristic.py
tests/gatt/test_descriptor.py
tests/gatt/test_service.py
bluez_peripheral-0.1.7.dist-info/LICENSE
bluez_peripheral-0.1.7.dist-info/METADATA
bluez_peripheral-0.1.7.dist-info/WHEEL
bluez_peripheral-0.1.7.dist-info/top_level.txt
bluez_peripheral-0.1.7.dist-info/RECORD
