Metadata-Version: 2.1
Name: bluez-peripheral
Version: 0.1.7
Summary: A library for building BLE peripherals using GATT and bluez
Home-page: https://github.com/spacecheese/bluez_peripheral
Author: SpaceCheese
License: MIT License
Classifier: Programming Language :: Python :: 3
Classifier: License :: OSI Approved :: MIT License
Classifier: Typing :: Typed
License-File: LICENSE
